habito/__init__.py
habito/main.py
habito/models.py
habito/commands/__init__.py
habito/commands/add.py
habito/commands/checkin.py
habito/commands/delete.py
habito/commands/edit.py
habito/commands/list.py
habito-1.2.0.dist-info/LICENSE.md
habito-1.2.0.dist-info/METADATA
habito-1.2.0.dist-info/WHEEL
habito-1.2.0.dist-info/entry_points.txt
habito-1.2.0.dist-info/top_level.txt
habito-1.2.0.dist-info/RECORD
