Metadata-Version: 2.1
Name: habito
Version: 1.2.0
Summary: Simple command line habits tracker
Home-page: https://github.com/codito/habito
Author: Arun Mahapatra
Author-email: codito@codito.in
License: MIT
Keywords: habits goals track tracking quantified self
Classifier: Development Status :: 3 - Alpha
Classifier: Environment :: Console
Classifier: Intended Audience :: End Users/Desktop
Classifier: Intended Audience :: Developers
Classifier: License :: OSI Approved :: MIT License
Classifier: Operating System :: MacOS
Classifier: Operating System :: Microsoft
Classifier: Operating System :: POSIX :: Linux
Classifier: Programming Language :: Python :: 3 :: Only
Classifier: Programming Language :: Python :: 3
Classifier: Programming Language :: Python :: 3.10
Classifier: Programming Language :: Python :: 3.11
Classifier: Programming Language :: Python :: 3.12
Classifier: Topic :: Utilities
Requires-Python: >=3.5
License-File: LICENSE.md
Requires-Dist: click
Requires-Dist: peewee >=3.0.15
Requires-Dist: terminaltables
Requires-Dist: dateparser
